ndx_vame/spec/ndx-vame.extensions.yaml
ndx_vame/spec/ndx-vame.namespace.yaml
ndx_vame/__init__.py
ndx_vame-0.2.2.dist-info/METADATA
ndx_vame-0.2.2.dist-info/WHEEL
ndx_vame-0.2.2.dist-info/licenses/LICENSE.txt
ndx_vame-0.2.2.dist-info/RECORD
