Metadata-Version: 2.4
Name: ndx-vame
Version: 0.2.2
Summary: NWB extension for VAME
Project-URL: Homepage, https://github.com/catalystneuro/ndx-vame
Project-URL: Documentation, https://ndx-vame.readthedocs.io/
Project-URL: Bug Tracker, https://github.com/catalystneuro/ndx-vame/issues
Project-URL: Discussions, https://github.com/catalystneuro/ndx-vame/discussions
Project-URL: Changelog, https://github.com/catalystneuro/ndx-vame/blob/main/CHANGELOG.md
Author-email: Luiz Tauffer <luiz.tauffer@catalystneuro.com>
License-Expression: MIT
License-File: LICENSE.txt
Keywords: NWB,NeurodataWithoutBorders,ndx-extension,nwb-extension
Classifier: Intended Audience :: Developers
Classifier: Intended Audience :: Science/Research
Classifier: License :: OSI Approved :: MIT License
Classifier: Programming Language :: Python :: 3.11
Classifier: Programming Language :: Python :: 3.12
Classifier: Programming Language :: Python :: 3.13
Requires-Python: >=3.9
Requires-Dist: hdmf>=3.14.1
Requires-Dist: ndx-pose>=0.2.2
Requires-Dist: pynwb>=2.8.0
Provides-Extra: dev
Requires-Dist: black>=24.4.2; extra == 'dev'
Requires-Dist: codespell>=2.3.0; extra == 'dev'
Requires-Dist: coverage>=7.5.4; extra == 'dev'
Requires-Dist: hdmf-docutils==0.4.8; extra == 'dev'
Requires-Dist: pre-commit>=3.5.0; extra == 'dev'
Requires-Dist: pytest-cov>=5.0.0; extra == 'dev'
Requires-Dist: pytest-subtests>=0.12.1; extra == 'dev'
Requires-Dist: pytest>=8.2.2; extra == 'dev'
Requires-Dist: python-dateutil>=2.8.2; extra == 'dev'
Requires-Dist: ruff>=0.4.10; extra == 'dev'
Requires-Dist: sphinx-rtd-theme==3.0.2; extra == 'dev'
Provides-Extra: docs
Requires-Dist: hdmf-docutils==0.4.8; extra == 'docs'
Requires-Dist: sphinx-rtd-theme==3.0.2; extra == 'docs'
Provides-Extra: min-reqs
Requires-Dist: hdmf==3.14.1; extra == 'min-reqs'
Requires-Dist: ndx-pose>=0.2.2; extra == 'min-reqs'
Requires-Dist: pynwb==2.8.0; extra == 'min-reqs'
Provides-Extra: test
Requires-Dist: coverage>=7.5.4; extra == 'test'
Requires-Dist: pytest-cov>=5.0.0; extra == 'test'
Requires-Dist: pytest-subtests>=0.12.1; extra == 'test'
Requires-Dist: pytest>=8.2.2; extra == 'test'
Requires-Dist: python-dateutil>=2.8.2; extra == 'test'
